huatule.py
setup.py
huatule.egg-info/PKG-INFO
huatule.egg-info/SOURCES.txt
huatule.egg-info/dependency_links.txt
huatule.egg-info/top_level.txt