Metadata-Version: 1.0
Name: huatule
Version: 0.1.2
Summary: a tool for patent trend
Home-page: https://pypi.org/manage/projects/
Author: qqqq
Author-email: 1412187956@qq.com
License: MIT License
Keywords: patent
Platform: UNKNOWN
